hashed_cron/__init__.py
hashed_cron/cron_converter.py
hashed_cron-0.4.0.dist-info/METADATA
hashed_cron-0.4.0.dist-info/WHEEL
hashed_cron-0.4.0.dist-info/top_level.txt
hashed_cron-0.4.0.dist-info/RECORD
