Metadata-Version: 2.4
Name: hashed-cron
Version: 0.4.0
Summary: Utility library to convert Hashed Crons, using 'H' character.
Home-page: https://github.com/thiagowig/hashed-cron
Author: Thiago Fonseca
Author-email: dev.thiago@gmail.com
License: MIT
Classifier: License :: OSI Approved :: MIT License
Classifier: Programming Language :: Python :: 3
Classifier: Programming Language :: Python :: 3.7
Dynamic: author
Dynamic: author-email
Dynamic: classifier
Dynamic: description
Dynamic: description-content-type
Dynamic: home-page
Dynamic: license
Dynamic: summary
